pytorch_pkg_helpers/__init__.py
pytorch_pkg_helpers/__main__.py
pytorch_pkg_helpers/conda.py
pytorch_pkg_helpers/cuda.py
pytorch_pkg_helpers/macos.py
pytorch_pkg_helpers/utils.py
pytorch_pkg_helpers/version.py
pytorch_pkg_helpers/wheel.py
pytorch_pkg_helpers-0.1.5.dist-info/entry_points.txt
pytorch_pkg_helpers-0.1.5.dist-info/WHEEL
pytorch_pkg_helpers-0.1.5.dist-info/METADATA
pytorch_pkg_helpers-0.1.5.dist-info/RECORD
